larango/__init__.py
larango/__main__.py
larango/commands/__init__.py
larango/commands/help.py
larango/utils/__init__.py
larango/utils/colors.py
Larango-0.1.3.dist-info/LICENSE
Larango-0.1.3.dist-info/METADATA
Larango-0.1.3.dist-info/WHEEL
Larango-0.1.3.dist-info/entry_points.txt
Larango-0.1.3.dist-info/top_level.txt
Larango-0.1.3.dist-info/RECORD
