Metadata-Version: 2.1
Name: Larango
Version: 0.1.3
Summary: Larango Web Framework
Home-page: https://github.com/mosab-jbara/larango
Author: Mosab Jbara
Author-email: mosabjbara@gmail.com
License: UNKNOWN
Platform: UNKNOWN
Requires-Python: >=3.6, <4
License-File: LICENSE
Requires-Dist: Django (==4.0)
